CHANGELOG.md
CITATION.cff
README.md
SPRpy/DEFAULT_X_cal_values.csv
SPRpy/SPRpy.py
SPRpy/SPRpy_X_cal.py
SPRpy/SPRpy_classes.py
SPRpy/SPRpy_functions.py
SPRpy/SPRpy_spr2_to_csv.py
SPRpy/__about__.py
SPRpy/__init__.py
SPRpy/config.toml
SPRpy/config.toml.backup
SPRpy/create_desktop_shortcut.py
SPRpy/fresnel_transfer_matrix.py
SPRpy/assets/bootstrap_spacelab.css
SPRpy/assets/icon.ico
SPRpy/example data/Example_height_probing_data.spr2
SPRpy/static/images/SPR-sensor.PNG
SPRpy/static/images/SPR_angular_spectrum.svg
SPRpy/static/images/SPR_principle.svg
SPRpy/static/images/fresnel_material.svg
SPRpy/static/images/icon.png
SPRpy/static/images/icon.svg
SPRpy/static/images/non-interacting_height_probe.PNG
venv3/Lib/site-packages/flask/sansio/README.md
venv_py12/Lib/site-packages/flask/sansio/README.md
venv_py12/Lib/site-packages/kaleido/vendor/mathjax/README.md
sprpy-1.1.3.dist-info/METADATA
sprpy-1.1.3.dist-info/WHEEL
sprpy-1.1.3.dist-info/entry_points.txt
sprpy-1.1.3.dist-info/licenses/LICENSE
sprpy-1.1.3.dist-info/RECORD
