Metadata-Version: 2.4
Name: SPRpy
Version: 1.1.3
Summary: SPRpy is an open-source project developing GUI data analysis tools for multi-parameter surface plasmon resonance measurements.  
Project-URL: Documentation, https://github.com/John-trailinghyphon/SPRpy#readme
Project-URL: ReleaseNotes, https://github.com/John-trailinghyphon/SPRpy/blob/master/CHANGELOG.md
Project-URL: Issues, https://github.com/John-trailinghyphon/SPRpy/issues
Project-URL: Source, https://github.com/John-trailinghyphon/SPRpy
Author-email: John Andersson <anjohn@chalmers.se>
License-Expression: MIT
License-File: LICENSE
Keywords: Dash,Data Analysis,GUI,Python,SPR,Surface Plasmon Resonance
Classifier: Development Status :: 3 - Alpha
Classifier: Intended Audience :: Science/Research
Classifier: License :: OSI Approved :: MIT License
Classifier: Operating System :: OS Independent
Classifier: Programming Language :: Python :: 3.11
Classifier: Programming Language :: Python :: 3.12
Classifier: Topic :: Scientific/Engineering :: Chemistry
Classifier: Topic :: Scientific/Engineering :: Information Analysis
Requires-Python: <3.13,>=3.11
Requires-Dist: bottleneck>=1.3.7
Requires-Dist: dash-bootstrap-components==1.7.1
Requires-Dist: dash==2.18.2
Requires-Dist: kaleido>=0.1.0.post1
Requires-Dist: numpy>=1.26.2
Requires-Dist: pandas>=2.1.4
Requires-Dist: plotly>=5.16.1
Requires-Dist: pywin32; platform_system == 'Windows'
Requires-Dist: scipy>=1.11.2
